ghga_event_schemas/__init__.py
ghga_event_schemas/pydantic_.py
ghga_event_schemas/validation.py
ghga_event_schemas/configs/__init__.py
ghga_event_schemas/configs/stateful.py
ghga_event_schemas/configs/stateless.py
ghga_event_schemas-11.0.0.dist-info/licenses/LICENSE
ghga_event_schemas-11.0.0.dist-info/METADATA
ghga_event_schemas-11.0.0.dist-info/WHEEL
ghga_event_schemas-11.0.0.dist-info/top_level.txt
ghga_event_schemas-11.0.0.dist-info/RECORD
