Metadata-Version: 2.4
Name: ghga_event_schemas
Version: 11.0.0
Summary: GHGA Event Schemas: A package that collects schemas used for events exchanged between GHGA service.
Author-email: "German Human Genome Phenome Archive (GHGA)" <contact@ghga.de>
License: Apache 2.0
Project-URL: Repository, https://github.com/ghga-de/ghga-event-schemas
Classifier: Development Status :: 5 - Production/Stable
Classifier: Operating System :: POSIX :: Linux
Classifier: Programming Language :: Python :: 3
Classifier: Programming Language :: Python :: 3.12
Classifier: License :: OSI Approved :: Apache Software License
Classifier: Topic :: Internet :: WWW/HTTP :: HTTP Servers
Classifier: Topic :: Software Development :: Libraries
Classifier: Intended Audience :: Developers
Requires-Python: >=3.12
License-File: LICENSE
Requires-Dist: jsonschema<5.0.0,>=4.23.0
Requires-Dist: pydantic[email]<3,>=2
Requires-Dist: pydantic_settings<3,>=2
Requires-Dist: ghga-service-commons>=5.0.0
Dynamic: license-file
